{
  "lastUpdated": 1746134540736,
  "cookieSets": [
    {
      "name": "X-AB",
      "value": "3cb966ee1aab40cf8f205dde72ec4578",
      "domain": "sc-static.net",
      "path": "/scevent.min.js",
      "expires": 1746220840.896,
      "httpOnly": false,
      "secure": true,
      "sameSite": "None",
      "expiry": 1746220840.896,
      "cookies": [
        {
          "name": "X-AB",
          "value": "3cb966ee1aab40cf8f205dde72ec4578",
          "domain": "sc-static.net",
          "path": "/scevent.min.js",
          "expires": 1746220840.896,
          "httpOnly": false,
          "secure": true,
          "sameSite": "None",
          "expiry": 1746220840.896
        },
        {
          "name": "eps_sid",
          "value": "b028eba15863a2b3e497121afab3fc08ef83a769",
          "domain": ".ticketmaster.com",
          "path": "/",
          "expires": 1746220840.896,
          "httpOnly": true,
          "secure": false,
          "sameSite": "Lax",
          "expiry": 1746220840.896
        },
        {
          "name": "_gcl_au",
          "value": "1.1.1450015407.1746134415",
          "domain": ".ticketmaster.com",
          "path": "/",
          "expires": 1746220840.896,
          "httpOnly": false,
          "secure": false,
          "sameSite": "Lax",
          "expiry": 1746220840.896
        },
        {
          "name": "tmpt",
          "value": "0:e2ef613cbe000000:1746134416:330ef250:a85e5efdd7b6d3b235026d1371dc1c35:2ab9344d64073901c43638a10ffc7a4e528e6704a96f37b1b9a3f8ce1718d184",
          "domain": ".ticketmaster.com",
          "path": "/",
          "expires": 1746220840.896,
          "httpOnly": false,
          "secure": false,
          "sameSite": "Lax",
          "expiry": 1746220840.896
        },
        {
          "name": "epsfc",
          "value": "1",
          "domain": "www.ticketmaster.com",
          "path": "/",
          "expires": 1746220840.896,
          "httpOnly": true,
          "secure": true,
          "sameSite": "None",
          "expiry": 1746220840.896
        },
        {
          "name": "SID",
          "value": "B-Unxm_N9e5_kF511ji8u5TDEog2VWr6KJGVRK2dyxe2eKLkjvpEAMuI4P17IFs5UaqEG6gwJ6jjoo1N",
          "domain": ".ticketmaster.com",
          "path": "/",
          "expires": 1746220840.896,
          "httpOnly": true,
          "secure": true,
          "sameSite": "None",
          "expiry": 1746220840.896
        },
        {
          "name": "lightstep_guid%2Fco2.sdk",
          "value": "2551eb875513887b",
          "domain": "www.ticketmaster.com",
          "path": "/",
          "expires": 1746220840.896,
          "httpOnly": false,
          "secure": false,
          "sameSite": "Lax",
          "expiry": 1746220840.896
        },
        {
          "name": "lightstep_session_id",
          "value": "248d8ea961f05c22",
          "domain": "www.ticketmaster.com",
          "path": "/",
          "expires": 1746220840.896,
          "httpOnly": false,
          "secure": false,
          "sameSite": "Lax",
          "expiry": 1746220840.896
        },
        {
          "name": "mt.v",
          "value": "2.2001784386.1746134423867",
          "domain": ".ticketmaster.com",
          "path": "/",
          "expires": 1746220840.896,
          "httpOnly": false,
          "secure": false,
          "sameSite": "Lax",
          "expiry": 1746220840.896
        },
        {
          "name": "mt.pc",
          "value": "2.1",
          "domain": ".ticketmaster.com",
          "path": "/",
          "expires": 1746220840.896,
          "httpOnly": false,
          "secure": false,
          "sameSite": "Lax",
          "expiry": 1746220840.896
        },
        {
          "name": "_ga_C1T806G4DF",
          "value": "GS1.1.1746134419.1.1.1746134425.54.0.0",
          "domain": ".ticketmaster.com",
          "path": "/",
          "expires": 1746220840.896,
          "httpOnly": false,
          "secure": true,
          "sameSite": "None",
          "expiry": 1746220840.896
        },
        {
          "name": "_ga_H1KKSGW33X",
          "value": "GS1.1.1746134419.1.1.1746134425.54.0.0",
          "domain": ".ticketmaster.com",
          "path": "/",
          "expires": 1746220840.896,
          "httpOnly": false,
          "secure": true,
          "sameSite": "None",
          "expiry": 1746220840.896
        },
        {
          "name": "TMUO",
          "value": "east_iTL3Wh+j0XIh4YD6u2HD4R/cOGlDghyAQb2ciFy+I0E=",
          "domain": ".ticketmaster.com",
          "path": "/",
          "expires": 1746220840.896,
          "httpOnly": true,
          "secure": true,
          "sameSite": "Lax",
          "expiry": 1746220840.896
        },
        {
          "name": "mt.g.2f013145",
          "value": "2.2001784386.1746134423867",
          "domain": ".ticketmaster.com",
          "path": "/",
          "expires": 1746220840.896,
          "httpOnly": false,
          "secure": false,
          "sameSite": "Lax",
          "expiry": 1746220840.896
        },
        {
          "name": "_ga",
          "value": "GA1.2.1111004427.1746134419",
          "domain": ".ticketmaster.com",
          "path": "/",
          "expires": 1746220840.896,
          "httpOnly": false,
          "secure": true,
          "sameSite": "None",
          "expiry": 1746220840.896
        },
        {
          "name": "_gid",
          "value": "GA1.2.1571296907.1746134432",
          "domain": ".ticketmaster.com",
          "path": "/",
          "expires": 1746220840.896,
          "httpOnly": false,
          "secure": true,
          "sameSite": "None",
          "expiry": 1746220840.896
        },
        {
          "name": "_dc_gtm_UA-60025178-1",
          "value": "1",
          "domain": ".ticketmaster.com",
          "path": "/",
          "expires": 1746220840.896,
          "httpOnly": false,
          "secure": true,
          "sameSite": "None",
          "expiry": 1746220840.896
        },
        {
          "name": "_fbp",
          "value": "fb.1.1746134434562.849623393712624841",
          "domain": ".ticketmaster.com",
          "path": "/",
          "expires": 1746220840.896,
          "httpOnly": false,
          "secure": false,
          "sameSite": "Lax",
          "expiry": 1746220840.896
        },
        {
          "name": "TDID",
          "value": "b38b4860-4869-485f-9d7b-b4866ca27b30",
          "domain": ".adsrvr.org",
          "path": "/",
          "expires": 1746220840.896,
          "httpOnly": false,
          "secure": true,
          "sameSite": "None",
          "expiry": 1746220840.896
        },
        {
          "name": "_au_1d",
          "value": "AU1D0200001746134435UUP8SCTL21UA",
          "domain": ".ticketmaster.com",
          "path": "/",
          "expires": 1746220840.896,
          "httpOnly": false,
          "secure": true,
          "sameSite": "None",
          "expiry": 1746220840.896
        },
        {
          "name": "tuuid",
          "value": "48bd822f-4b59-45cf-b6c6-79b89247f7ff",
          "domain": ".bidswitch.net",
          "path": "/",
          "expires": 1746220840.896,
          "httpOnly": false,
          "secure": true,
          "sameSite": "None",
          "expiry": 1746220840.896
        },
        {
          "name": "c",
          "value": "1746134435",
          "domain": ".bidswitch.net",
          "path": "/",
          "expires": 1746220840.896,
          "httpOnly": false,
          "secure": true,
          "sameSite": "None",
          "expiry": 1746220840.896
        },
        {
          "name": "tuuid_lu",
          "value": "1746134435",
          "domain": ".bidswitch.net",
          "path": "/",
          "expires": 1746220840.896,
          "httpOnly": false,
          "secure": true,
          "sameSite": "None",
          "expiry": 1746220840.896
        },
        {
          "name": "test_cookie",
          "value": "CheckForPermission",
          "domain": ".doubleclick.net",
          "path": "/",
          "expires": 1746220840.896,
          "httpOnly": true,
          "secure": true,
          "sameSite": "None",
          "expiry": 1746220840.896
        },
        {
          "name": "audit_p",
          "value": "1|dIyXnjtg4UnqQYOPXH/RnuTotPTE1Y5cOUzUQcSdAjsqAA8m177YZMV0RaxoISggRmyVUsY5xv6M1KxoLazIt9i2Wk5FrGos0XY24Ec+XLvRQicGVOUMTN6y2YjBhwWSwxx70mkm4Qv9V2ydVAAdm3dgD1Vrj9WvmNl/1iGzYadbOz6AjJtUa8ZnH3r7x5VAdeodiyl5GGjkt77VmXBK7kiCfUmSYXqD+ohH/uuQN8oOr/S07bYDcYQkZmofZQkSVSwKu1RXSJT0/fhu8/pkBO4VeIulq+4M1TRwmTZWV3Xc6UO785F0Pw==",
          "domain": ".rubiconproject.com",
          "path": "/",
          "expires": 1746220840.896,
          "httpOnly": false,
          "secure": true,
          "sameSite": "None",
          "expiry": 1746220840.896
        },
        {
          "name": "khaos",
          "value": "MA5VCXW8-J-D7P5",
          "domain": ".rubiconproject.com",
          "path": "/",
          "expires": 1746220840.896,
          "httpOnly": false,
          "secure": true,
          "sameSite": "None",
          "expiry": 1746220840.896
        },
        {
          "name": "khaos_p",
          "value": "MA5VCXW8-J-D7P5",
          "domain": ".rubiconproject.com",
          "path": "/",
          "expires": 1746220840.896,
          "httpOnly": false,
          "secure": true,
          "sameSite": "None",
          "expiry": 1746220840.896
        },
        {
          "name": "audit",
          "value": "1|dIyXnjtg4UnqQYOPXH/RnuTotPTE1Y5cOUzUQcSdAjsqAA8m177YZMV0RaxoISggRmyVUsY5xv6M1KxoLazIt9i2Wk5FrGos0XY24Ec+XLvRQicGVOUMTN6y2YjBhwWSwxx70mkm4Qv9V2ydVAAdm3dgD1Vrj9WvmNl/1iGzYadbOz6AjJtUa8ZnH3r7x5VAdeodiyl5GGjkt77VmXBK7kiCfUmSYXqD+ohH/uuQN8oOr/S07bYDcYQkZmofZQkSVSwKu1RXSJT0/fhu8/pkBO4VeIulq+4M1TRwmTZWV3Xc6UO785F0Pw==",
          "domain": ".rubiconproject.com",
          "path": "/",
          "expires": 1746220840.896,
          "httpOnly": false,
          "secure": true,
          "sameSite": "None",
          "expiry": 1746220840.896
        },
        {
          "name": "TM_PIXEL",
          "value": "{\"_dvs\":\"0:ma5vcz0s:4p33NTVT8o6SUL~DTibpON4dSrqV2hMJ\",\"_dvp\":\"0:ma5vcz0s:bGW2usfmXlzUD7uIE_xX7Q50Wx5jINF~\"}",
          "domain": ".ticketmaster.com",
          "path": "/",
          "expires": 1746220840.896,
          "httpOnly": false,
          "secure": true,
          "sameSite": "Lax",
          "expiry": 1746220840.896
        },
        {
          "name": "_dvs",
          "value": "0:ma5vcz0s:4p33NTVT8o6SUL~DTibpON4dSrqV2hMJ",
          "domain": "www.ticketmaster.com",
          "path": "/",
          "expires": 1746220840.896,
          "httpOnly": false,
          "secure": false,
          "sameSite": "Lax",
          "expiry": 1746220840.896
        },
        {
          "name": "_dvp",
          "value": "0:ma5vcz0s:bGW2usfmXlzUD7uIE_xX7Q50Wx5jINF~",
          "domain": "www.ticketmaster.com",
          "path": "/",
          "expires": 1746220840.896,
          "httpOnly": false,
          "secure": false,
          "sameSite": "Lax",
          "expiry": 1746220840.896
        },
        {
          "name": "seerses",
          "value": "e",
          "domain": ".www.ticketmaster.com",
          "path": "/",
          "expires": 1746220840.896,
          "httpOnly": false,
          "secure": false,
          "sameSite": "Lax",
          "expiry": 1746220840.896
        },
        {
          "name": "barometric[cuid]",
          "value": "cuid_6813e5a5-a704-42c1-8737-489c88d48ab3",
          "domain": ".trkn.us",
          "path": "/",
          "expires": 1746220840.896,
          "httpOnly": false,
          "secure": true,
          "sameSite": "None",
          "expiry": 1746220840.896
        },
        {
          "name": "_dc_gtm_UA-60025178-2",
          "value": "1",
          "domain": ".ticketmaster.com",
          "path": "/",
          "expires": 1746220840.896,
          "httpOnly": false,
          "secure": true,
          "sameSite": "None",
          "expiry": 1746220840.896
        },
        {
          "name": "TDCPM",
          "value": "CAESFQoGZ29vZ2xlEgsIuN3A3aGSgj4QBRIWCgdydWJpY29uEgsI6uLmtIHAhD4QBRIYCgliaWRzd2l0Y2gSCwjSk-e0gcCEPhAFEhcKCHB1Ym1hdGljEgsIqP2tyIHAhD4QBRIVCgZjYXNhbGUSCwiQ-LLOgcCEPhAFGAUoBjILCJjZj_6XwIQ-EAVCDyINCAESCQoFdGllcjIQAVoHdzkwNXpud2AB",
          "domain": ".adsrvr.org",
          "path": "/",
          "expires": 1746220840.896,
          "httpOnly": false,
          "secure": true,
          "sameSite": "None",
          "expiry": 1746220840.896
        },
        {
          "name": "CMID",
          "value": "aBPlphdaRFsAF-eCCTkNMwAA",
          "domain": ".casalemedia.com",
          "path": "/",
          "expires": 1746220840.896,
          "httpOnly": false,
          "secure": true,
          "sameSite": "None",
          "expiry": 1746220840.896
        },
        {
          "name": "CMPS",
          "value": "5400",
          "domain": ".casalemedia.com",
          "path": "/",
          "expires": 1746220840.896,
          "httpOnly": false,
          "secure": true,
          "sameSite": "None",
          "expiry": 1746220840.896
        },
        {
          "name": "CMPRO",
          "value": "5400",
          "domain": ".casalemedia.com",
          "path": "/",
          "expires": 1746220840.896,
          "httpOnly": false,
          "secure": true,
          "sameSite": "None",
          "expiry": 1746220840.896
        },
        {
          "name": "REMARKET-ADV-10346",
          "value": "[{\"adv_aud_id\":\"10346\",\"adv_pid\":\"K8vZ9175rX7\",\"adv_cid\":\"KovZpZAF6tIA\",\"adv_bid\":\"vv1F8Zb_3pa8Zd2vk\",\"adv_gid\":\"0\"}]",
          "domain": ".advanseads.com",
          "path": "/",
          "expires": 1746220840.896,
          "httpOnly": false,
          "secure": true,
          "sameSite": "None",
          "expiry": 1746220840.896
        },
        {
          "name": "ADV-BCID",
          "value": "7b13cabd-327d-4d4d-ba93-0147f1924c11",
          "domain": ".advanseads.com",
          "path": "/",
          "expires": 1746220840.896,
          "httpOnly": false,
          "secure": true,
          "sameSite": "None",
          "expiry": 1746220840.896
        },
        {
          "name": "_scid",
          "value": "no3jjVkQqiOIgwmSaalr3p6SrwvjBwHy",
          "domain": ".ticketmaster.com",
          "path": "/",
          "expires": 1746220840.896,
          "httpOnly": false,
          "secure": false,
          "sameSite": "Lax",
          "expiry": 1746220840.896
        },
        {
          "name": "SID",
          "value": "wvOvtQoTn-UDBxrR1O-6dqX31Cynf5_mto9mx9f9zKyphxvQQc6C1UZOWO-xLtnISFWpcOaIZBOvQZIv",
          "domain": ".mapsapi.tmol.io",
          "path": "/",
          "expires": 1746220840.896,
          "httpOnly": true,
          "secure": true,
          "sameSite": "None",
          "expiry": 1746220840.896
        },
        {
          "name": "_ttp",
          "value": "2wVl5WlLpJdmU1N0TIkXr69dPGk",
          "domain": ".tiktok.com",
          "path": "/",
          "expires": 1746220840.896,
          "httpOnly": false,
          "secure": true,
          "sameSite": "None",
          "expiry": 1746220840.896
        },
        {
          "name": "ad-id",
          "value": "AxMC5hQNUEJ1rkx-erIVHb8",
          "domain": ".amazon-adsystem.com",
          "path": "/",
          "expires": 1746220840.896,
          "httpOnly": true,
          "secure": true,
          "sameSite": "None",
          "expiry": 1746220840.896
        },
        {
          "name": "ad-privacy",
          "value": "0",
          "domain": ".amazon-adsystem.com",
          "path": "/",
          "expires": 1746220840.896,
          "httpOnly": true,
          "secure": true,
          "sameSite": "None",
          "expiry": 1746220840.896
        },
        {
          "name": "ph",
          "value": "%7B%22p%22%3A%5B%5D%2C%22t%22%3A%5B%5D%7D",
          "domain": ".yieldoptimizer.com",
          "path": "/",
          "expires": 1746220840.896,
          "httpOnly": false,
          "secure": true,
          "sameSite": "None",
          "expiry": 1746220840.896
        },
        {
          "name": "fbh0",
          "value": "%7B%7D",
          "domain": ".yieldoptimizer.com",
          "path": "/",
          "expires": 1746220840.896,
          "httpOnly": false,
          "secure": true,
          "sameSite": "None",
          "expiry": 1746220840.896
        },
        {
          "name": "dph",
          "value": "%7B%22t%22%3A%5B%5D%2C%22dp%22%3A%5B%5D%7D",
          "domain": ".yieldoptimizer.com",
          "path": "/",
          "expires": 1746220840.896,
          "httpOnly": false,
          "secure": true,
          "sameSite": "None",
          "expiry": 1746220840.896
        },
        {
          "name": "gcma",
          "value": "%7B%22t%22%3A0%2C%22o%22%3Afalse%7D",
          "domain": ".yieldoptimizer.com",
          "path": "/",
          "expires": 1746220840.896,
          "httpOnly": false,
          "secure": true,
          "sameSite": "None",
          "expiry": 1746220840.896
        },
        {
          "name": "rmxc",
          "value": "%7B%22t%22%3A0%2C%22e%22%3A%22%22%2C%22i%22%3Afalse%7D",
          "domain": ".yieldoptimizer.com",
          "path": "/",
          "expires": 1746220840.896,
          "httpOnly": false,
          "secure": true,
          "sameSite": "None",
          "expiry": 1746220840.896
        },
        {
          "name": "cktst",
          "value": "968291921",
          "domain": ".yieldoptimizer.com",
          "path": "/",
          "expires": 1746220840.896,
          "httpOnly": false,
          "secure": true,
          "sameSite": "None",
          "expiry": 1746220840.896
        },
        {
          "name": "sc_at",
          "value": "v2|H4sIAAAAAAAAAAXBgQ3AIAhFwYlIPvCi7TiidQqG7512hg5uVfca+qY9qW1R6wzI9RLdPhmegFo/781dGDIAAAA=",
          "domain": ".snapchat.com",
          "path": "/",
          "expires": 1746220840.896,
          "httpOnly": false,
          "secure": true,
          "sameSite": "None",
          "expiry": 1746220840.896
        },
        {
          "name": "_scid_r",
          "value": "lw3jjVkQqiOIgwmSaalr3p6SrwvjBwHyJJF4HQ",
          "domain": ".ticketmaster.com",
          "path": "/",
          "expires": 1746220840.896,
          "httpOnly": false,
          "secure": false,
          "sameSite": "Lax",
          "expiry": 1746220840.896
        },
        {
          "name": "_pn",
          "value": "eyJzdWIiOnsidWRyIjowLCJzcyI6MH0sImx1YSI6MTc0NjEzNDQ0MDcyMH0",
          "domain": ".ticketmaster.com",
          "path": "/",
          "expires": 1746220840.896,
          "httpOnly": false,
          "secure": false,
          "sameSite": "Strict",
          "expiry": 1746220840.896
        },
        {
          "name": "_rdt_uuid",
          "value": "1746134440736.a481fc64-d6ac-42c0-aeb6-d87986449c58",
          "domain": ".ticketmaster.com",
          "path": "/",
          "expires": 1746220840.896,
          "httpOnly": false,
          "secure": true,
          "sameSite": "Strict",
          "expiry": 1746220840.896
        }
      ],
      "timestamp": 1746134540736
    },
    {
      "name": "eps_sid",
      "value": "b028eba15863a2b3e497121afab3fc08ef83a769",
      "domain": ".ticketmaster.com",
      "path": "/",
      "expires": 1746220840.896,
      "httpOnly": true,
      "secure": false,
      "sameSite": "Lax",
      "expiry": 1746220840.896
    },
    {
      "name": "_gcl_au",
      "value": "1.1.1450015407.1746134415",
      "domain": ".ticketmaster.com",
      "path": "/",
      "expires": 1746220840.896,
      "httpOnly": false,
      "secure": false,
      "sameSite": "Lax",
      "expiry": 1746220840.896
    },
    {
      "name": "tmpt",
      "value": "0:e2ef613cbe000000:1746134416:330ef250:a85e5efdd7b6d3b235026d1371dc1c35:2ab9344d64073901c43638a10ffc7a4e528e6704a96f37b1b9a3f8ce1718d184",
      "domain": ".ticketmaster.com",
      "path": "/",
      "expires": 1746220840.896,
      "httpOnly": false,
      "secure": false,
      "sameSite": "Lax",
      "expiry": 1746220840.896
    },
    {
      "name": "epsfc",
      "value": "1",
      "domain": "www.ticketmaster.com",
      "path": "/",
      "expires": 1746220840.896,
      "httpOnly": true,
      "secure": true,
      "sameSite": "None",
      "expiry": 1746220840.896
    },
    {
      "name": "SID",
      "value": "B-Unxm_N9e5_kF511ji8u5TDEog2VWr6KJGVRK2dyxe2eKLkjvpEAMuI4P17IFs5UaqEG6gwJ6jjoo1N",
      "domain": ".ticketmaster.com",
      "path": "/",
      "expires": 1746220840.896,
      "httpOnly": true,
      "secure": true,
      "sameSite": "None",
      "expiry": 1746220840.896
    },
    {
      "name": "lightstep_guid%2Fco2.sdk",
      "value": "2551eb875513887b",
      "domain": "www.ticketmaster.com",
      "path": "/",
      "expires": 1746220840.896,
      "httpOnly": false,
      "secure": false,
      "sameSite": "Lax",
      "expiry": 1746220840.896
    },
    {
      "name": "lightstep_session_id",
      "value": "248d8ea961f05c22",
      "domain": "www.ticketmaster.com",
      "path": "/",
      "expires": 1746220840.896,
      "httpOnly": false,
      "secure": false,
      "sameSite": "Lax",
      "expiry": 1746220840.896
    },
    {
      "name": "mt.v",
      "value": "2.2001784386.1746134423867",
      "domain": ".ticketmaster.com",
      "path": "/",
      "expires": 1746220840.896,
      "httpOnly": false,
      "secure": false,
      "sameSite": "Lax",
      "expiry": 1746220840.896
    },
    {
      "name": "mt.pc",
      "value": "2.1",
      "domain": ".ticketmaster.com",
      "path": "/",
      "expires": 1746220840.896,
      "httpOnly": false,
      "secure": false,
      "sameSite": "Lax",
      "expiry": 1746220840.896
    },
    {
      "name": "_ga_C1T806G4DF",
      "value": "GS1.1.1746134419.1.1.1746134425.54.0.0",
      "domain": ".ticketmaster.com",
      "path": "/",
      "expires": 1746220840.896,
      "httpOnly": false,
      "secure": true,
      "sameSite": "None",
      "expiry": 1746220840.896
    },
    {
      "name": "_ga_H1KKSGW33X",
      "value": "GS1.1.1746134419.1.1.1746134425.54.0.0",
      "domain": ".ticketmaster.com",
      "path": "/",
      "expires": 1746220840.896,
      "httpOnly": false,
      "secure": true,
      "sameSite": "None",
      "expiry": 1746220840.896
    },
    {
      "name": "TMUO",
      "value": "east_iTL3Wh+j0XIh4YD6u2HD4R/cOGlDghyAQb2ciFy+I0E=",
      "domain": ".ticketmaster.com",
      "path": "/",
      "expires": 1746220840.896,
      "httpOnly": true,
      "secure": true,
      "sameSite": "Lax",
      "expiry": 1746220840.896
    },
    {
      "name": "mt.g.2f013145",
      "value": "2.2001784386.1746134423867",
      "domain": ".ticketmaster.com",
      "path": "/",
      "expires": 1746220840.896,
      "httpOnly": false,
      "secure": false,
      "sameSite": "Lax",
      "expiry": 1746220840.896
    },
    {
      "name": "_ga",
      "value": "GA1.2.1111004427.1746134419",
      "domain": ".ticketmaster.com",
      "path": "/",
      "expires": 1746220840.896,
      "httpOnly": false,
      "secure": true,
      "sameSite": "None",
      "expiry": 1746220840.896
    },
    {
      "name": "_gid",
      "value": "GA1.2.1571296907.1746134432",
      "domain": ".ticketmaster.com",
      "path": "/",
      "expires": 1746220840.896,
      "httpOnly": false,
      "secure": true,
      "sameSite": "None",
      "expiry": 1746220840.896
    },
    {
      "name": "_dc_gtm_UA-60025178-1",
      "value": "1",
      "domain": ".ticketmaster.com",
      "path": "/",
      "expires": 1746220840.896,
      "httpOnly": false,
      "secure": true,
      "sameSite": "None",
      "expiry": 1746220840.896
    },
    {
      "name": "_fbp",
      "value": "fb.1.1746134434562.849623393712624841",
      "domain": ".ticketmaster.com",
      "path": "/",
      "expires": 1746220840.896,
      "httpOnly": false,
      "secure": false,
      "sameSite": "Lax",
      "expiry": 1746220840.896
    },
    {
      "name": "TDID",
      "value": "b38b4860-4869-485f-9d7b-b4866ca27b30",
      "domain": ".adsrvr.org",
      "path": "/",
      "expires": 1746220840.896,
      "httpOnly": false,
      "secure": true,
      "sameSite": "None",
      "expiry": 1746220840.896
    },
    {
      "name": "_au_1d",
      "value": "AU1D0200001746134435UUP8SCTL21UA",
      "domain": ".ticketmaster.com",
      "path": "/",
      "expires": 1746220840.896,
      "httpOnly": false,
      "secure": true,
      "sameSite": "None",
      "expiry": 1746220840.896
    },
    {
      "name": "tuuid",
      "value": "48bd822f-4b59-45cf-b6c6-79b89247f7ff",
      "domain": ".bidswitch.net",
      "path": "/",
      "expires": 1746220840.896,
      "httpOnly": false,
      "secure": true,
      "sameSite": "None",
      "expiry": 1746220840.896
    },
    {
      "name": "c",
      "value": "1746134435",
      "domain": ".bidswitch.net",
      "path": "/",
      "expires": 1746220840.896,
      "httpOnly": false,
      "secure": true,
      "sameSite": "None",
      "expiry": 1746220840.896
    },
    {
      "name": "tuuid_lu",
      "value": "1746134435",
      "domain": ".bidswitch.net",
      "path": "/",
      "expires": 1746220840.896,
      "httpOnly": false,
      "secure": true,
      "sameSite": "None",
      "expiry": 1746220840.896
    },
    {
      "name": "test_cookie",
      "value": "CheckForPermission",
      "domain": ".doubleclick.net",
      "path": "/",
      "expires": 1746220840.896,
      "httpOnly": true,
      "secure": true,
      "sameSite": "None",
      "expiry": 1746220840.896
    },
    {
      "name": "audit_p",
      "value": "1|dIyXnjtg4UnqQYOPXH/RnuTotPTE1Y5cOUzUQcSdAjsqAA8m177YZMV0RaxoISggRmyVUsY5xv6M1KxoLazIt9i2Wk5FrGos0XY24Ec+XLvRQicGVOUMTN6y2YjBhwWSwxx70mkm4Qv9V2ydVAAdm3dgD1Vrj9WvmNl/1iGzYadbOz6AjJtUa8ZnH3r7x5VAdeodiyl5GGjkt77VmXBK7kiCfUmSYXqD+ohH/uuQN8oOr/S07bYDcYQkZmofZQkSVSwKu1RXSJT0/fhu8/pkBO4VeIulq+4M1TRwmTZWV3Xc6UO785F0Pw==",
      "domain": ".rubiconproject.com",
      "path": "/",
      "expires": 1746220840.896,
      "httpOnly": false,
      "secure": true,
      "sameSite": "None",
      "expiry": 1746220840.896
    },
    {
      "name": "khaos",
      "value": "MA5VCXW8-J-D7P5",
      "domain": ".rubiconproject.com",
      "path": "/",
      "expires": 1746220840.896,
      "httpOnly": false,
      "secure": true,
      "sameSite": "None",
      "expiry": 1746220840.896
    },
    {
      "name": "khaos_p",
      "value": "MA5VCXW8-J-D7P5",
      "domain": ".rubiconproject.com",
      "path": "/",
      "expires": 1746220840.896,
      "httpOnly": false,
      "secure": true,
      "sameSite": "None",
      "expiry": 1746220840.896
    },
    {
      "name": "audit",
      "value": "1|dIyXnjtg4UnqQYOPXH/RnuTotPTE1Y5cOUzUQcSdAjsqAA8m177YZMV0RaxoISggRmyVUsY5xv6M1KxoLazIt9i2Wk5FrGos0XY24Ec+XLvRQicGVOUMTN6y2YjBhwWSwxx70mkm4Qv9V2ydVAAdm3dgD1Vrj9WvmNl/1iGzYadbOz6AjJtUa8ZnH3r7x5VAdeodiyl5GGjkt77VmXBK7kiCfUmSYXqD+ohH/uuQN8oOr/S07bYDcYQkZmofZQkSVSwKu1RXSJT0/fhu8/pkBO4VeIulq+4M1TRwmTZWV3Xc6UO785F0Pw==",
      "domain": ".rubiconproject.com",
      "path": "/",
      "expires": 1746220840.896,
      "httpOnly": false,
      "secure": true,
      "sameSite": "None",
      "expiry": 1746220840.896
    },
    {
      "name": "TM_PIXEL",
      "value": "{\"_dvs\":\"0:ma5vcz0s:4p33NTVT8o6SUL~DTibpON4dSrqV2hMJ\",\"_dvp\":\"0:ma5vcz0s:bGW2usfmXlzUD7uIE_xX7Q50Wx5jINF~\"}",
      "domain": ".ticketmaster.com",
      "path": "/",
      "expires": 1746220840.896,
      "httpOnly": false,
      "secure": true,
      "sameSite": "Lax",
      "expiry": 1746220840.896
    },
    {
      "name": "_dvs",
      "value": "0:ma5vcz0s:4p33NTVT8o6SUL~DTibpON4dSrqV2hMJ",
      "domain": "www.ticketmaster.com",
      "path": "/",
      "expires": 1746220840.896,
      "httpOnly": false,
      "secure": false,
      "sameSite": "Lax",
      "expiry": 1746220840.896
    },
    {
      "name": "_dvp",
      "value": "0:ma5vcz0s:bGW2usfmXlzUD7uIE_xX7Q50Wx5jINF~",
      "domain": "www.ticketmaster.com",
      "path": "/",
      "expires": 1746220840.896,
      "httpOnly": false,
      "secure": false,
      "sameSite": "Lax",
      "expiry": 1746220840.896
    },
    {
      "name": "seerses",
      "value": "e",
      "domain": ".www.ticketmaster.com",
      "path": "/",
      "expires": 1746220840.896,
      "httpOnly": false,
      "secure": false,
      "sameSite": "Lax",
      "expiry": 1746220840.896
    },
    {
      "name": "barometric[cuid]",
      "value": "cuid_6813e5a5-a704-42c1-8737-489c88d48ab3",
      "domain": ".trkn.us",
      "path": "/",
      "expires": 1746220840.896,
      "httpOnly": false,
      "secure": true,
      "sameSite": "None",
      "expiry": 1746220840.896
    },
    {
      "name": "_dc_gtm_UA-60025178-2",
      "value": "1",
      "domain": ".ticketmaster.com",
      "path": "/",
      "expires": 1746220840.896,
      "httpOnly": false,
      "secure": true,
      "sameSite": "None",
      "expiry": 1746220840.896
    },
    {
      "name": "TDCPM",
      "value": "CAESFQoGZ29vZ2xlEgsIuN3A3aGSgj4QBRIWCgdydWJpY29uEgsI6uLmtIHAhD4QBRIYCgliaWRzd2l0Y2gSCwjSk-e0gcCEPhAFEhcKCHB1Ym1hdGljEgsIqP2tyIHAhD4QBRIVCgZjYXNhbGUSCwiQ-LLOgcCEPhAFGAUoBjILCJjZj_6XwIQ-EAVCDyINCAESCQoFdGllcjIQAVoHdzkwNXpud2AB",
      "domain": ".adsrvr.org",
      "path": "/",
      "expires": 1746220840.896,
      "httpOnly": false,
      "secure": true,
      "sameSite": "None",
      "expiry": 1746220840.896
    },
    {
      "name": "CMID",
      "value": "aBPlphdaRFsAF-eCCTkNMwAA",
      "domain": ".casalemedia.com",
      "path": "/",
      "expires": 1746220840.896,
      "httpOnly": false,
      "secure": true,
      "sameSite": "None",
      "expiry": 1746220840.896
    },
    {
      "name": "CMPS",
      "value": "5400",
      "domain": ".casalemedia.com",
      "path": "/",
      "expires": 1746220840.896,
      "httpOnly": false,
      "secure": true,
      "sameSite": "None",
      "expiry": 1746220840.896
    },
    {
      "name": "CMPRO",
      "value": "5400",
      "domain": ".casalemedia.com",
      "path": "/",
      "expires": 1746220840.896,
      "httpOnly": false,
      "secure": true,
      "sameSite": "None",
      "expiry": 1746220840.896
    },
    {
      "name": "REMARKET-ADV-10346",
      "value": "[{\"adv_aud_id\":\"10346\",\"adv_pid\":\"K8vZ9175rX7\",\"adv_cid\":\"KovZpZAF6tIA\",\"adv_bid\":\"vv1F8Zb_3pa8Zd2vk\",\"adv_gid\":\"0\"}]",
      "domain": ".advanseads.com",
      "path": "/",
      "expires": 1746220840.896,
      "httpOnly": false,
      "secure": true,
      "sameSite": "None",
      "expiry": 1746220840.896
    },
    {
      "name": "ADV-BCID",
      "value": "7b13cabd-327d-4d4d-ba93-0147f1924c11",
      "domain": ".advanseads.com",
      "path": "/",
      "expires": 1746220840.896,
      "httpOnly": false,
      "secure": true,
      "sameSite": "None",
      "expiry": 1746220840.896
    },
    {
      "name": "_scid",
      "value": "no3jjVkQqiOIgwmSaalr3p6SrwvjBwHy",
      "domain": ".ticketmaster.com",
      "path": "/",
      "expires": 1746220840.896,
      "httpOnly": false,
      "secure": false,
      "sameSite": "Lax",
      "expiry": 1746220840.896
    },
    {
      "name": "SID",
      "value": "wvOvtQoTn-UDBxrR1O-6dqX31Cynf5_mto9mx9f9zKyphxvQQc6C1UZOWO-xLtnISFWpcOaIZBOvQZIv",
      "domain": ".mapsapi.tmol.io",
      "path": "/",
      "expires": 1746220840.896,
      "httpOnly": true,
      "secure": true,
      "sameSite": "None",
      "expiry": 1746220840.896
    },
    {
      "name": "_ttp",
      "value": "2wVl5WlLpJdmU1N0TIkXr69dPGk",
      "domain": ".tiktok.com",
      "path": "/",
      "expires": 1746220840.896,
      "httpOnly": false,
      "secure": true,
      "sameSite": "None",
      "expiry": 1746220840.896
    },
    {
      "name": "ad-id",
      "value": "AxMC5hQNUEJ1rkx-erIVHb8",
      "domain": ".amazon-adsystem.com",
      "path": "/",
      "expires": 1746220840.896,
      "httpOnly": true,
      "secure": true,
      "sameSite": "None",
      "expiry": 1746220840.896
    },
    {
      "name": "ad-privacy",
      "value": "0",
      "domain": ".amazon-adsystem.com",
      "path": "/",
      "expires": 1746220840.896,
      "httpOnly": true,
      "secure": true,
      "sameSite": "None",
      "expiry": 1746220840.896
    },
    {
      "name": "ph",
      "value": "%7B%22p%22%3A%5B%5D%2C%22t%22%3A%5B%5D%7D",
      "domain": ".yieldoptimizer.com",
      "path": "/",
      "expires": 1746220840.896,
      "httpOnly": false,
      "secure": true,
      "sameSite": "None",
      "expiry": 1746220840.896
    },
    {
      "name": "fbh0",
      "value": "%7B%7D",
      "domain": ".yieldoptimizer.com",
      "path": "/",
      "expires": 1746220840.896,
      "httpOnly": false,
      "secure": true,
      "sameSite": "None",
      "expiry": 1746220840.896
    },
    {
      "name": "dph",
      "value": "%7B%22t%22%3A%5B%5D%2C%22dp%22%3A%5B%5D%7D",
      "domain": ".yieldoptimizer.com",
      "path": "/",
      "expires": 1746220840.896,
      "httpOnly": false,
      "secure": true,
      "sameSite": "None",
      "expiry": 1746220840.896
    },
    {
      "name": "gcma",
      "value": "%7B%22t%22%3A0%2C%22o%22%3Afalse%7D",
      "domain": ".yieldoptimizer.com",
      "path": "/",
      "expires": 1746220840.896,
      "httpOnly": false,
      "secure": true,
      "sameSite": "None",
      "expiry": 1746220840.896
    },
    {
      "name": "rmxc",
      "value": "%7B%22t%22%3A0%2C%22e%22%3A%22%22%2C%22i%22%3Afalse%7D",
      "domain": ".yieldoptimizer.com",
      "path": "/",
      "expires": 1746220840.896,
      "httpOnly": false,
      "secure": true,
      "sameSite": "None",
      "expiry": 1746220840.896
    },
    {
      "name": "cktst",
      "value": "968291921",
      "domain": ".yieldoptimizer.com",
      "path": "/",
      "expires": 1746220840.896,
      "httpOnly": false,
      "secure": true,
      "sameSite": "None",
      "expiry": 1746220840.896
    },
    {
      "name": "sc_at",
      "value": "v2|H4sIAAAAAAAAAAXBgQ3AIAhFwYlIPvCi7TiidQqG7512hg5uVfca+qY9qW1R6wzI9RLdPhmegFo/781dGDIAAAA=",
      "domain": ".snapchat.com",
      "path": "/",
      "expires": 1746220840.896,
      "httpOnly": false,
      "secure": true,
      "sameSite": "None",
      "expiry": 1746220840.896
    },
    {
      "name": "_scid_r",
      "value": "lw3jjVkQqiOIgwmSaalr3p6SrwvjBwHyJJF4HQ",
      "domain": ".ticketmaster.com",
      "path": "/",
      "expires": 1746220840.896,
      "httpOnly": false,
      "secure": false,
      "sameSite": "Lax",
      "expiry": 1746220840.896
    },
    {
      "name": "_pn",
      "value": "eyJzdWIiOnsidWRyIjowLCJzcyI6MH0sImx1YSI6MTc0NjEzNDQ0MDcyMH0",
      "domain": ".ticketmaster.com",
      "path": "/",
      "expires": 1746220840.896,
      "httpOnly": false,
      "secure": false,
      "sameSite": "Strict",
      "expiry": 1746220840.896
    },
    {
      "name": "_rdt_uuid",
      "value": "1746134440736.a481fc64-d6ac-42c0-aeb6-d87986449c58",
      "domain": ".ticketmaster.com",
      "path": "/",
      "expires": 1746220840.896,
      "httpOnly": false,
      "secure": true,
      "sameSite": "Strict",
      "expiry": 1746220840.896
    }
  ]
}