{
  "schema": "urn:com.ticketmaster.services:schema:ismds:EventOffer:1.0",
  "meta": {
    "type": "urn:com.ticketmaster.services:type:ismds:EventOffer",
    "modified": "2025-05-11T13:20:31.838542763Z",
    "expires": "2025-05-11T13:30:31.838542763Z"
  },
  "offerId": "GJ6DC7BVGA",
  "name": "Standard Ticket",
  "rank": 0,
  "online": true,
  "protected": false,
  "rollup": false,
  "inventoryType": "primary",
  "offerType": "standard",
  "ticketTypeId": "000000000001",
  "auditPriceLevel": "3",
  "priceLevelId": "50",
  "priceLevelSecname": "P3",
  "description": "Standard Ticket",
  "currency": "USD",
  "listPrice": 74.5,
  "faceValue": 74.5,
  "totalPrice": 99.05,
  "noChargesPrice": 74.5,
  "charges": [
    {
      "reason": "order_processing",
      "type": "fee",
      "subType": "default",
      "amount": 0
    },
    {
      "reason": "service",
      "type": "fee",
      "amount": 17.95
    },
    {
      "reason": "service_tax",
      "type": "tax",
      "amount": 1.6
    },
    {
      "reason": "facility",
      "type": "fee",
      "amount": 5
    }
  ],
  "sellableQuantities": [
    1,
    2,
    3,
    4,
    5,
    6,
    7,
    8
  ],
  "alternateIds": [],
  "_links": {
    "self": [
      {
        "href": "/host/0E00616E747A1458/offers/GJ6DC7BVGA"
      }
    ],
    "event": [
      {
        "href": "/event/0E00616E747A1458"
      }
    ],
    "tickettype": [
      {
        "href": "/host/0E00616E747A1458/tickettypes/000000000001"
      }
    ]
  }
}